controller.v
module controller (
    input [6:0] opcode,
    output reg ALUscr, memToReg, regWrite, memRead, memWrite, branch, 
    output reg [1:0] ALUop
);
    // --------METHOD 1--------
    //assign opcode = instruction[6:0];
    /*
    always @* begin
     if (opcode  == 7'b0110011) begin           // for R-type
      {ALUscr, memToReg, regWrite, memRead, memWrite, branch, ALUop} <= 8'b00100010;
    end else if (opcode == 7'b0000011) begin   // for I-type
      {ALUscr, memToReg, regWrite, memRead, memWrite, branch, ALUop} <= 8'b11110000;
    end else if (opcode == 7'b0100011) begin   // for S-type
      {ALUscr, memToReg, regWrite, memRead, memWrite, branch, ALUop} <= 8'b1x001000;
    end else if (opcode == 7'b1100011) begin   // for SB-type
      {ALUscr, memToReg, regWrite, memRead, memWrite, branch, ALUop} <= 8'b0x000101;
    end   
    end
    */
    // -------METHIOD 2---------  
     always @ (opcode or ALUscr or memToReg or regWrite or memRead or memWrite or branch or ALUop )  
     begin       
       case ( opcode )   
     7'b0110011  :   {ALUscr, memToReg, regWrite, memRead, memWrite, branch, ALUop} <= 8'b00100010;  // for R-type
     7'b0000011  :   {ALUscr, memToReg, regWrite, memRead, memWrite, branch, ALUop} <= 8'b11110000;  // for I-type
     7'b0100011  :   {ALUscr, memToReg, regWrite, memRead, memWrite, branch, ALUop} <= 8'b1x001000;  // for S-type
     7'b1100011  :   {ALUscr, memToReg, regWrite, memRead, memWrite, branch, ALUop} <= 8'b0x000101;  // for SB-type
       endcase          
     end 
  
endmodule

ALUcntrl.v
module ALUcntrl (
    input [1:0] ALUop,
    input [6:0] func7,
    input [2:0] func3,
    output reg [3:0] alu_opcode
);

   always @* begin
             if ((ALUop  == 2'b00) /*& (func7 == 7'bx) & (func3 == 3'bx)*/) begin 
      alu_opcode = 4'b0010;
    end else if ((ALUop[0]  == 1) /*& (func7 == 7'bx) & (func3 == 3'bx)*/) begin 
      alu_opcode = 4'b0110;
    end else if ((ALUop[1]  == 1) & (func7 == 7'b0) & (func3 == 3'b0)) begin 
      alu_opcode = 4'b0010;
    end else if ((ALUop[1]  == 1) & (func7 == 7'b0100000) & (func3 == 3'b0)) begin 
      alu_opcode = 4'b0110;
    end else if ((ALUop[1]  == 1) & (func7 == 7'b0) & (func3 == 3'b111)) begin 
      alu_opcode = 4'b0000;
    end else if ((ALUop[1]  == 1) & (func7 == 7'b0) & (func3 == 3'b110)) begin 
      alu_opcode = 4'b0001;
    end 
   end
      
endmodule

dataMem.v
module dataMem (
  input reset, clock, wEn,
  input [31:0] address, dataWrite,
  output [31:0] dataRead
);
     reg [31:0] memory [1023:0];

always @(posedge clock ) begin

    if (wEn) begin
        memory[address] <= dataWrite;
     end 
  end
  
     assign dataRead = (reset) ? 32'h0 : memory[address];

  initial begin
    memory[12] = 32'h0000000f;
  end
    // integer i;
    // // initial begin   // initializing data memory
    // //   for (i = 0; i < 1023; i = i + 1) begin
    // //     memory[i] = 32'h00000001 + (i*4);
    // //   end 
    // end
    

endmodule

ALU.v
module alu ( 
   input [3:0]  alu_opcode,
   input [31:0] in_a , in_b, 
   output reg [31:0] alu_out  
 );
    always @ ( in_a or in_b or alu_opcode or alu_out )  
     begin       
       case ( alu_opcode )   
     4'h0   :  alu_out = in_a & in_b;
     4'h1   :  alu_out = in_a | in_b;
     4'h2   :  alu_out = in_a + in_b;
     4'h6   :  alu_out = in_a - in_b;   
       endcase          
     end 
  
 endmodule

mux.v
module mux (
input sel,
input [31:0] in0, in1,
output [31:0] mux_out
);

assign  mux_out = (sel) ? in0 : in1;

endmodule

immGen.v
module immGen (
   input [31:0] inst,
   output reg [31:0] GenOut
);

   // Concatenate the bits as intended
   always @* begin
      
   if (inst[5]) begin
    GenOut = (inst[31] == 1'b1) ? {{20{1'b1}}, inst[31:25], inst[11:7]} : {{20{1'b0}}, inst[31:25], inst[11:7]};
   end else begin
    GenOut = (inst[31] == 1'b1) ? {{20{1'b1}}, inst[31:20]} : {{20{1'b0}}, inst[31:20]};
   end
   end

endmodule

regFile.v
module regFile (
  input clock, reset, wEn,
  input [31:0] write_data,
  input [4:0] read_reg1, read_reg2, write_reg,
  output [31:0] read_data1, read_data2
);

  reg [31:0] reg_file[31:0];
  integer k;
  
always @(posedge clock ) begin
        if (wEn) begin
            reg_file[write_reg] <= write_data;
        end
    end
  
    assign read_data1 = (reset == 0) ? reg_file[read_reg1] : 0;
    assign read_data2 = (reset == 0) ? reg_file[read_reg2] : 0;

    initial begin
        reg_file[6] = 32'h00000007;
        reg_file[5] = 32'h0000000d;    
    end

endmodule

instrMem.v
module instrMem (
   input [31:0] address,
   input reset,
   output [31:0] instruction
);
  reg [31:0] inst_mem [1023:0];  // Define a memory array to store instructions

  integer i;

  initial begin
  //  for (i = 0; i < 1023; i = i + 4 ) begin
      // Example R-type instruction: ADD R3, R1, R2 
      inst_mem[0] = 32'h00536823;   //0000 0000 0101 0011 0110 1000 0010 0011 - S
      inst_mem[4] = 32'h00536833;   //0000 0000 0101 0011 0110 1000 0011 0011 - R
      inst_mem[8] = 32'h00536803;   //0000 0000 0101 0011 0110 1000 0000 0011 - I
      inst_mem[12] = 32'h00536863;  //0000 0000 0101 0011 0110 1000 0110 0011 - SB
  // end
  end

  assign instruction = (reset == 1'b1) ? 32'b0 : inst_mem[address];

endmodule

PCfetch.v
module PCfetch(
  input  clock,
  input  reset,
  input  branch,
  input  [31:0] target_PC,
  output [31:0] PC
);

   reg [31:0] PC_reg;
   assign PC = PC_reg;

always @(posedge clock ) begin
  if (reset) begin
      PC_reg <= 32'b0;
  end else if(~branch) begin 
      PC_reg <= PC_reg + 4'b0100;
  end else if(branch) begin
      PC_reg = target_PC;
end
end
  
endmodule

SCP_RISCV_main.v
`include "PCfetch.v"
`include "regFile.v"
`include "instrMem.v"
`include "dataMem.v"
`include "ALU.v"
`include "mux.v"
`include "ALUcntrl.v"
`include "controller.v"
`include "immGen.v"

module SCP_RISCV_main (clock, wEn, reset, address);
    input  clock, reset, wEn;
    input  [31:0] address;  

    wire ALUscr, memToReg, regWrite, memRead, memWrite, branch;
    wire [1:0] ALUop1;
    wire [31:0] PC, instruction1, read_data01, read_data02, dataRead1, alu_out1, mux_out1, mux_out2, immGen_out;
    wire [3:0] alu_opcode1 ;


 PCfetch PC1(
        .clock(clock),
        .reset(reset),
        .branch(branch),
        .target_PC(address),
        .PC(PC)       
    );

 instrMem Instmem(
        .address(PC),
        .reset(reset),
        .instruction(instruction1)
    );

 regFile Regfile(
        .clock(clock),
        .reset(reset),
        .wEn(regWrite),
        .write_data(mux_out2),
        .read_reg1(instruction1[19:15]), 
        .read_reg2(instruction1[24:20]), 
        .write_reg(instruction1[11:7]),
        .read_data1(read_data01), 
        .read_data2(read_data02)
    );

 immGen immi_gen (
       .inst(instruction1),
       .GenOut(immGen_out)
);

 mux mux1(
        .sel(ALUscr),
        .in0(immGen_out), 
        .in1(read_data02),
        .mux_out(mux_out1)
    );

 mux mux2(
        .sel(memToReg),
        .in0(dataRead1), 
        .in1(alu_out1),
        .mux_out(mux_out2)
    );

 alu alu1( 
        .alu_opcode(alu_opcode1),
        .in_a(read_data01),
        .in_b(mux_out1), 
        .alu_out(alu_out1) 
    );

 dataMem DataMem(
        .clock(clock),
        .reset(reset),
        .wEn(memWrite),
        .address(alu_out1), 
        .dataWrite(read_data02),
        .dataRead(dataRead1)
    );
    
 ALUcntrl ALUcontrol (
        .ALUop(ALUop1),
        .func7(instruction1[31:25]),
        .func3(instruction1[14:12]),
        .alu_opcode(alu_opcode1)
    );
 
 controller mainController(
        .opcode(instruction1[6:0]),
        .ALUscr(ALUscr), 
        .memToReg(memToReg), 
        .regWrite(regWrite), 
        .memRead(memRead), 
        .memWrite(memWrite), 
        .branch(branch), 
        .ALUop(ALUop1)
);
    
endmodule

SCP_RISCV_testbench.v
 `include "SCP_RISCV_main.v"

`timescale 1ns/1ps

module tb_SCP_RISCV_main;

  // Define clock and reset signals
  reg clock , reset, wEn;
  reg [31:0] address;

  // Instantiate your CSP_RISCV_main processor
  SCP_RISCV_main csp (
    .clock(clock),
    .wEn(wEn),
    .reset(reset),
    .address(address) // Connect your 32-bit address input
  );

  initial repeat (8) begin #5 clock=1; #5 clock=0; end
 
    initial @(posedge clock ) begin

     $display("--------SINGLE CYCLE RISC-V PROCESSOR TESTING--------");

    $monitor("At time %0d reset=%b wEn=%b, address %h: PC = %h, Instruction = %h, alu_opcode = %b, alu_out = %h, DataRead = %h",
           $time, reset, wEn, address, csp.PC, csp.instruction1, csp.alu_opcode1, csp.alu_out1, csp.dataRead1); 

    reset = 1; wEn = 1; address = 32'h00000001;  @(posedge clock) 
    reset = 0; wEn = 1; address = 32'h00000002;  @(posedge clock) 
    reset = 1; wEn = 0; address = 32'h00000004;  @(posedge clock) 
    reset = 0; wEn = 1; address = 32'h00000008;  @(posedge clock) 
    reset = 0; wEn = 0; address = 32'h0000000b;  @(posedge clock) 
    reset = 0; wEn = 1; address = 32'h00000010;  @(posedge clock) 
    reset = 0; wEn = 1; address = 32'h00000016;  @(posedge clock) 
    reset = 1; wEn = 1; address = 32'h00000000;  @(posedge clock) 
  
    $display("TEST PASSED");
    $finish;
    end
    
    initial begin
    $dumpvars;
    $dumpfile("dump.vcd");
    end  

endmodule

build/dump.vcd
$date
	Wed Sep 20 21:04:25 2023
$end
$version
	Icarus Verilog
$end
$timescale
	1ps
$end
$scope module tb_SCP_RISCV_main $end
$var reg 32 ! address [31:0] $end
$var reg 1 " clock $end
$var reg 1 # reset $end
$var reg 1 $ wEn $end
$scope module csp $end
$var wire 32 % address [31:0] $end
$var wire 1 " clock $end
$var wire 1 # reset $end
$var wire 1 $ wEn $end
$var wire 1 & regWrite $end
$var wire 32 ' read_data02 [31:0] $end
$var wire 32 ( read_data01 [31:0] $end
$var wire 32 ) mux_out2 [31:0] $end
$var wire 32 * mux_out1 [31:0] $end
$var wire 1 + memWrite $end
$var wire 1 , memToReg $end
$var wire 1 - memRead $end
$var wire 32 . instruction1 [31:0] $end
$var wire 32 / immGen_out [31:0] $end
$var wire 32 0 dataRead1 [31:0] $end
$var wire 1 1 branch $end
$var wire 32 2 alu_out1 [31:0] $end
$var wire 4 3 alu_opcode1 [3:0] $end
$var wire 32 4 PC [31:0] $end
$var wire 1 5 ALUscr $end
$var wire 2 6 ALUop1 [1:0] $end
$scope module ALUcontrol $end
$var wire 3 7 func3 [2:0] $end
$var wire 7 8 func7 [6:0] $end
$var wire 2 9 ALUop [1:0] $end
$var reg 4 : alu_opcode [3:0] $end
$upscope $end
$scope module DataMem $end
$var wire 1 " clock $end
$var wire 1 # reset $end
$var wire 1 + wEn $end
$var wire 32 ; dataWrite [31:0] $end
$var wire 32 < dataRead [31:0] $end
$var wire 32 = address [31:0] $end
$upscope $end
$scope module Instmem $end
$var wire 1 # reset $end
$var wire 32 > instruction [31:0] $end
$var wire 32 ? address [31:0] $end
$upscope $end
$scope module PC1 $end
$var wire 1 " clock $end
$var wire 1 # reset $end
$var wire 32 @ target_PC [31:0] $end
$var wire 1 1 branch $end
$var wire 32 A PC [31:0] $end
$var reg 32 B PC_reg [31:0] $end
$upscope $end
$scope module Regfile $end
$var wire 1 " clock $end
$var wire 5 C read_reg1 [4:0] $end
$var wire 5 D read_reg2 [4:0] $end
$var wire 1 # reset $end
$var wire 5 E write_reg [4:0] $end
$var wire 32 F write_data [31:0] $end
$var wire 1 & wEn $end
$var wire 32 G read_data2 [31:0] $end
$var wire 32 H read_data1 [31:0] $end
$upscope $end
$scope module alu1 $end
$var wire 4 I alu_opcode [3:0] $end
$var wire 32 J in_a [31:0] $end
$var wire 32 K in_b [31:0] $end
$var reg 32 L alu_out [31:0] $end
$upscope $end
$scope module immi_gen $end
$var wire 32 M inst [31:0] $end
$var reg 32 N GenOut [31:0] $end
$upscope $end
$scope module mainController $end
$var wire 7 O opcode [6:0] $end
$var reg 2 P ALUop [1:0] $end
$var reg 1 5 ALUscr $end
$var reg 1 1 branch $end
$var reg 1 - memRead $end
$var reg 1 , memToReg $end
$var reg 1 + memWrite $end
$var reg 1 & regWrite $end
$upscope $end
$scope module mux1 $end
$var wire 32 Q in0 [31:0] $end
$var wire 32 R in1 [31:0] $end
$var wire 1 5 sel $end
$var wire 32 S mux_out [31:0] $end
$upscope $end
$scope module mux2 $end
$var wire 32 T in0 [31:0] $end
$var wire 32 U in1 [31:0] $end
$var wire 1 , sel $end
$var wire 32 V mux_out [31:0] $end
$upscope $end
$upscope $end
$upscope $end
$enddefinitions $end
$comment Show the parameter values. $end
$dumpall
$end
#0
$dumpvars
bx V
bx U
bx T
bx S
bx R
bx Q
bx P
bx O
bx N
bx M
bx L
bx K
bx J
bx I
bx H
bx G
bx F
bx E
bx D
bx C
bx B
bx A
bx @
bx ?
bx >
bx =
bx <
bx ;
bx :
bx 9
bx 8
bx 7
bx 6
x5
bx 4
bx 3
bx 2
x1
bx 0
bx /
bx .
x-
x,
x+
bx *
bx )
bx (
bx '
x&
bx %
x$
x#
x"
bx !
$end
#5000
b0 4
b0 ?
b0 A
b0 B
b0 *
b0 K
b0 S
b0 O
b0 7
b0 8
b0 E
b0 D
b0 C
b0 /
b0 N
b0 Q
b0 .
b0 >
b0 M
b0 0
b0 <
b0 T
b0 (
b0 H
b0 J
b0 '
b0 ;
b0 G
b0 R
b1 !
b1 %
b1 @
1$
1#
1"
#10000
0"
#15000
b10111 2
b10111 =
b10111 L
b10111 U
b10 3
b10 :
b10 I
15
0&
0-
1+
01
b0 6
b0 9
b0 P
b100011 O
b110 7
b10000 E
b101 D
b110 C
b10000 /
b10000 N
b10000 Q
b10100110110100000100011 .
b10100110110100000100011 >
b10100110110100000100011 M
b10000 *
b10000 K
b10000 S
bx 0
bx <
bx T
b111 (
b111 H
b111 J
b1101 '
b1101 ;
b1101 G
b1101 R
b10 !
b10 %
b10 @
0#
1"
#20000
0"
#25000
b0 *
b0 K
b0 S
b0 O
b0 7
b0 E
b0 D
b0 C
b0 /
b0 N
b0 Q
b0 )
b0 F
b0 V
b0 .
b0 >
b0 M
b0 2
b0 =
b0 L
b0 U
b0 0
b0 <
b0 T
b0 (
b0 H
b0 J
b0 '
b0 ;
b0 G
b0 R
b100 !
b100 %
b100 @
0$
1#
1"
#30000
0"
#35000
b10000 *
b10000 K
b10000 S
b100011 O
b110 7
b10000 E
b101 D
b110 C
b10000 /
b10000 N
b10000 Q
b0xx1x1 )
b0xx1x1 F
b0xx1x1 V
b10100110110100000100011 .
b10100110110100000100011 >
b10100110110100000100011 M
b10111 2
b10111 =
b10111 L
b10111 U
b1101 0
b1101 <
b1101 T
b111 (
b111 H
b111 J
b1101 '
b1101 ;
b1101 G
b1101 R
b1000 !
b1000 %
b1000 @
1$
0#
1"
#40000
0"
#45000
bx 0
bx <
bx T
b1111 2
b1111 =
b1111 L
b1111 U
b1101 *
b1101 K
b1101 S
b1111 )
b1111 F
b1111 V
b1 3
b1 :
b1 I
05
0,
1&
0+
b10 6
b10 9
b10 P
b110011 O
b10100110110100000110011 .
b10100110110100000110011 >
b10100110110100000110011 M
b100 4
b100 ?
b100 A
b100 B
b1011 !
b1011 %
b1011 @
0$
1"
#50000
0"
#55000
b1111 0
b1111 <
b1111 T
b1100 2
b1100 =
b1100 L
b1100 U
b101 *
b101 K
b101 S
b1111 )
b1111 F
b1111 V
b10 3
b10 :
b10 I
15
1,
1-
b0 6
b0 9
b0 P
b11 O
b101 /
b101 N
b101 Q
b10100110110100000000011 .
b10100110110100000000011 >
b10100110110100000000011 M
b1000 4
b1000 ?
b1000 A
b1000 B
b10000 !
b10000 %
b10000 @
1$
1"
#60000
0"
#65000
b110 3
b110 :
b110 I
05
x,
0&
0-
11
b1 6
b1 9
b1 P
bx )
bx F
bx V
bx 0
bx <
bx T
b11111111111111111111111111111010 2
b11111111111111111111111111111010 =
b11111111111111111111111111111010 L
b11111111111111111111111111111010 U
b1101 *
b1101 K
b1101 S
b1100011 O
b10000 /
b10000 N
b10000 Q
b10100110110100001100011 .
b10100110110100001100011 >
b10100110110100001100011 M
b1100 4
b1100 ?
b1100 A
b1100 B
b10110 !
b10110 %
b10110 @
1"
#70000
0"
#75000
b0 )
b0 F
b0 V
b0 2
b0 =
b0 L
b0 U
b0 *
b0 K
b0 S
b0 O
b0 7
b0 8
b0 E
b0 D
b0 C
b0 /
b0 N
b0 Q
b0 0
b0 <
b0 T
b0 (
b0 H
b0 J
b0 '
b0 ;
b0 G
b0 R
b0 .
b0 >
b0 M
b0 !
b0 %
b0 @
1#
b10110 4
b10110 ?
b10110 A
b10110 B
1"
